genysis/__init__.py
genysis/client.py
genysis/legacy/__init__.py
genysis/legacy/adaptiveLattice.py
genysis/legacy/genysis.py
genysis/legacy/mesh.py
genysis/legacy/meshRepair.py
genysis/legacy/meshRepair_v2.py
genysis/legacy/parse_request.py
genysis-0.4.2.dist-info/DESCRIPTION.rst
genysis-0.4.2.dist-info/METADATA
genysis-0.4.2.dist-info/RECORD
genysis-0.4.2.dist-info/WHEEL
genysis-0.4.2.dist-info/metadata.json
genysis-0.4.2.dist-info/top_level.txt
