Metadata-Version: 2.0
Name: genysis
Version: 0.4.2
Summary: generative design
Home-page: UNKNOWN
Author: Li
Author-email: UNKNOWN
License: MIT
Platform: UNKNOWN
